{"cameraMode":{"drawMode":0,"name":"Shaded","section":"Shading Mode"},"sceneLighting":false,"audioPlay":false,"sceneViewState":{"m_AlwaysRefresh":false,"showFog":true,"showSkybox":false,"showFlares":true,"showImageEffects":true,"showParticleSystems":true,"showVisualEffectGraphs":true,"m_FxEnabled":true},"in2DMode":false,"pivot":{"x":0.5656964778900147,"y":1.568476915359497,"z":-1.6249291896820069},"rotation":{"x":0.0759434774518013,"y":0.923943817615509,"z":-0.27251115441322329,"w":0.2575036883354187},"size":1.5092053413391114,"orthographic":false}